<?xml version="1.0" encoding="UTF-8"?>
<PARAMDEF XmlVersion="0">
    <ParamType>BEHAVIOR_PARAM</ParamType>
    <DataVersion>12</DataVersion>
    <BigEndian>true</BigEndian>
    <Unicode>true</Unicode>
    <FormatVersion>105</FormatVersion>
    <Fields>
        <Field Def="s32 damageId00 = -1">
            <DisplayName>《行動0 ダメージID_1》</DisplayName>
            <DisplayFormat>%d</DisplayFormat>
            <EditFlags>Wrap</EditFlags>
            <Minimum>-1</Minimum>
            <Maximum>1e+09</Maximum>
            <Increment>1</Increment>
            <SortID>10000</SortID>
        </Field>
        <Field Def="s32 damageId01 = -1">
            <DisplayName>《行動0 ダメージID_2》</DisplayName>
            <DisplayFormat>%d</DisplayFormat>
            <EditFlags>Wrap</EditFlags>
            <Minimum>-1</Minimum>
            <Maximum>1e+09</Maximum>
            <Increment>1</Increment>
            <SortID>10000</SortID>
        </Field>
        <Field Def="s32 damageId02 = -1">
            <DisplayName>《行動0 ダメージID_3》</DisplayName>
            <DisplayFormat>%d</DisplayFormat>
            <EditFlags>Wrap</EditFlags>
            <Minimum>-1</Minimum>
            <Maximum>1e+09</Maximum>
            <Increment>1</Increment>
            <SortID>10000</SortID>
        </Field>
        <Field Def="s32 grabDamageId00 = -1">
            <DisplayName>《行動0 投げダメージID_1》</DisplayName>
            <DisplayFormat>%d</DisplayFormat>
            <EditFlags>Wrap</EditFlags>
            <Minimum>-1</Minimum>
            <Maximum>1e+09</Maximum>
            <Increment>1</Increment>
            <SortID>10000</SortID>
        </Field>
        <Field Def="s32 grabDamageId01 = -1">
            <DisplayName>《行動0 投げダメージID_2》</DisplayName>
            <DisplayFormat>%d</DisplayFormat>
            <EditFlags>Wrap</EditFlags>
            <Minimum>-1</Minimum>
            <Maximum>1e+09</Maximum>
            <Increment>1</Increment>
            <SortID>10000</SortID>
        </Field>
        <Field Def="s32 grabDamageId02 = -1">
            <DisplayName>《行動0 投げダメージID_3》</DisplayName>
            <DisplayFormat>%d</DisplayFormat>
            <EditFlags>Wrap</EditFlags>
            <Minimum>-1</Minimum>
            <Maximum>1e+09</Maximum>
            <Increment>1</Increment>
            <SortID>10000</SortID>
        </Field>
        <Field Def="u32 attackWalkMoveAttack">
            <DisplayName>《行動0 歩行攻撃ID》</DisplayName>
            <Enum>ENEMY_ATTACK_TYPE</Enum>
            <DisplayFormat>%d</DisplayFormat>
            <EditFlags>Wrap</EditFlags>
            <Maximum>9999999</Maximum>
            <Increment>1</Increment>
            <SortID>10000</SortID>
        </Field>
        <Field Def="u8 attackInvincible">
            <DisplayName>《行動0 割り込み不可タイプ》</DisplayName>
            <Enum>NON_INTERRUPTIBLE_TYPE</Enum>
            <EditFlags>Wrap</EditFlags>
            <Maximum>1</Maximum>
            <Increment>1</Increment>
            <SortID>10000</SortID>
        </Field>
        <Field Def="u8 handType">
            <DisplayName>《行動0 攻撃手》</DisplayName>
            <DisplayFormat>%d</DisplayFormat>
            <Maximum>1</Maximum>
            <Increment>1</Increment>
            <SortID>11000</SortID>
        </Field>
        <Field Def="u8 isSpell">
            <DisplayName>《行動0 スペルフラグ》</DisplayName>
            <Enum>BOOL_CIRCLECROSS_TYPE</Enum>
            <DisplayFormat>%d</DisplayFormat>
            <Maximum>1</Maximum>
            <Increment>1</Increment>
            <SortID>10210</SortID>
        </Field>
        <Field Def="u8 bladeCtrlType">
            <DisplayName>《行動0 近接制御タイプ》</DisplayName>
            <Enum>BLADE_CTRL_TYPE</Enum>
            <Maximum>9999</Maximum>
            <Increment>1</Increment>
            <SortID>10110</SortID>
        </Field>
        <Field Def="s32 bulletId00 = -1">
            <DisplayName>《行動0 BulletID_1》</DisplayName>
            <DisplayFormat>%d</DisplayFormat>
            <EditFlags>Wrap</EditFlags>
            <Minimum>-1</Minimum>
            <Maximum>1e+09</Maximum>
            <Increment>1</Increment>
            <SortID>10100</SortID>
        </Field>
        <Field Def="s32 bulletId01 = -1">
            <DisplayName>《行動0 BulletID_2》</DisplayName>
            <DisplayFormat>%d</DisplayFormat>
            <EditFlags>Wrap</EditFlags>
            <Minimum>-1</Minimum>
            <Maximum>1e+09</Maximum>
            <Increment>1</Increment>
            <SortID>10100</SortID>
        </Field>
        <Field Def="s32 bulletId02 = -1">
            <DisplayName>《行動0 BulletID_3》</DisplayName>
            <DisplayFormat>%d</DisplayFormat>
            <EditFlags>Wrap</EditFlags>
            <Minimum>-1</Minimum>
            <Maximum>1e+09</Maximum>
            <Increment>1</Increment>
            <SortID>10100</SortID>
        </Field>
        <Field Def="f32 shotStanceTime">
            <DisplayName>《行動0 射撃構え時間》</DisplayName>
            <DisplayFormat>%f</DisplayFormat>
            <EditFlags>Wrap</EditFlags>
            <Maximum>60</Maximum>
            <Increment>0.1</Increment>
            <SortID>10100</SortID>
        </Field>
        <Field Def="f32 attackRange = 1">
            <DisplayName>《行動0 歩行攻撃攻撃範囲》</DisplayName>
            <DisplayFormat>%f</DisplayFormat>
            <Maximum>9999</Maximum>
            <Increment>0.1</Increment>
            <SortID>10200</SortID>
        </Field>
        <Field Def="f32 fAttackBackSwingSpeed = 1">
            <DisplayName>《行動0 攻撃開始部速度倍率》</DisplayName>
            <DisplayFormat>%f</DisplayFormat>
            <Minimum>0.1</Minimum>
            <Maximum>9999</Maximum>
            <Increment>0.1</Increment>
            <SortID>10200</SortID>
        </Field>
        <Field Def="f32 fAttackFollowSwingSpeed = 1">
            <DisplayName>《行動0 攻撃終了部速度倍率》</DisplayName>
            <DisplayFormat>%f</DisplayFormat>
            <Minimum>0.1</Minimum>
            <Maximum>9999</Maximum>
            <Increment>0.1</Increment>
            <SortID>10200</SortID>
        </Field>
        <Field Def="f32 fAttackEstimateFutureTime">
            <DisplayName>《行動0 位置予測時間》</DisplayName>
            <DisplayFormat>%f</DisplayFormat>
            <Maximum>9999</Maximum>
            <Increment>0.1</Increment>
            <SortID>10200</SortID>
        </Field>
        <Field Def="angle32 fAttackAngle">
            <DisplayName>《行動0 角度補正[deg]》</DisplayName>
            <DisplayFormat>%f</DisplayFormat>
            <Minimum>-180</Minimum>
            <Maximum>180</Maximum>
            <Increment>0.1</Increment>
            <SortID>10200</SortID>
        </Field>
        <Field Def="f32 fAttackRotateHigh">
            <DisplayName>《行動0 旋回補間開始距離[m]》</DisplayName>
            <DisplayFormat>%f</DisplayFormat>
            <Maximum>100</Maximum>
            <Increment>0.1</Increment>
            <SortID>10200</SortID>
        </Field>
        <Field Def="f32 fAttackRotateLow">
            <DisplayName>《行動0 旋回補間終了距離[m]》</DisplayName>
            <DisplayFormat>%f</DisplayFormat>
            <Maximum>100</Maximum>
            <Increment>0.1</Increment>
            <SortID>10200</SortID>
        </Field>
        <Field Def="u32 chantSfx">
            <DisplayName>《行動0 詠唱SFX》</DisplayName>
            <Enum>ENEMY_SHOT_SFX_PARAM_ENUM</Enum>
            <DisplayFormat>%d</DisplayFormat>
            <Maximum>1</Maximum>
            <Increment>1</Increment>
            <SortID>10200</SortID>
        </Field>
        <Field Def="f32 reloadTimeMin">
            <DisplayName>《行動0 最小リロード時間》</DisplayName>
            <DisplayFormat>%f</DisplayFormat>
            <Maximum>999</Maximum>
            <Increment>0.1</Increment>
            <SortID>10300</SortID>
        </Field>
        <Field Def="f32 reloadTimeMax">
            <DisplayName>《行動0 最大リロード時間》</DisplayName>
            <DisplayFormat>%f</DisplayFormat>
            <Maximum>999</Maximum>
            <Increment>0.1</Increment>
            <SortID>10300</SortID>
        </Field>
        <Field Def="s32 damageId00 = -1">
            <DisplayName>《行動1 ダメージID_1》</DisplayName>
            <DisplayFormat>%d</DisplayFormat>
            <EditFlags>Wrap</EditFlags>
            <Minimum>-1</Minimum>
            <Maximum>1e+09</Maximum>
            <Increment>1</Increment>
            <SortID>20000</SortID>
        </Field>
        <Field Def="s32 damageId01 = -1">
            <DisplayName>《行動1 ダメージID_2》</DisplayName>
            <DisplayFormat>%d</DisplayFormat>
            <EditFlags>Wrap</EditFlags>
            <Minimum>-1</Minimum>
            <Maximum>1e+09</Maximum>
            <Increment>1</Increment>
            <SortID>20000</SortID>
        </Field>
        <Field Def="s32 damageId02 = -1">
            <DisplayName>《行動1 ダメージID_3》</DisplayName>
            <DisplayFormat>%d</DisplayFormat>
            <EditFlags>Wrap</EditFlags>
            <Minimum>-1</Minimum>
            <Maximum>1e+09</Maximum>
            <Increment>1</Increment>
            <SortID>20000</SortID>
        </Field>
        <Field Def="s32 grabDamageId00 = -1">
            <DisplayName>《行動1 投げダメージID_1》</DisplayName>
            <DisplayFormat>%d</DisplayFormat>
            <EditFlags>Wrap</EditFlags>
            <Minimum>-1</Minimum>
            <Maximum>1e+09</Maximum>
            <Increment>1</Increment>
            <SortID>20000</SortID>
        </Field>
        <Field Def="s32 grabDamageId01 = -1">
            <DisplayName>《行動1 投げダメージID_2》</DisplayName>
            <DisplayFormat>%d</DisplayFormat>
            <EditFlags>Wrap</EditFlags>
            <Minimum>-1</Minimum>
            <Maximum>1e+09</Maximum>
            <Increment>1</Increment>
            <SortID>20000</SortID>
        </Field>
        <Field Def="s32 grabDamageId02 = -1">
            <DisplayName>《行動1 投げダメージID_3》</DisplayName>
            <DisplayFormat>%d</DisplayFormat>
            <EditFlags>Wrap</EditFlags>
            <Minimum>-1</Minimum>
            <Maximum>1e+09</Maximum>
            <Increment>1</Increment>
            <SortID>20000</SortID>
        </Field>
        <Field Def="u32 attackWalkMoveAttack">
            <DisplayName>《行動1 歩行攻撃ID》</DisplayName>
            <Enum>ENEMY_ATTACK_TYPE</Enum>
            <DisplayFormat>%d</DisplayFormat>
            <EditFlags>Wrap</EditFlags>
            <Maximum>9999999</Maximum>
            <Increment>1</Increment>
            <SortID>20000</SortID>
        </Field>
        <Field Def="u8 attackInvincible">
            <DisplayName>《行動1 割り込み不可タイプ》</DisplayName>
            <Enum>NON_INTERRUPTIBLE_TYPE</Enum>
            <EditFlags>Wrap</EditFlags>
            <Maximum>1</Maximum>
            <Increment>1</Increment>
            <SortID>20000</SortID>
        </Field>
        <Field Def="u8 handType">
            <DisplayName>《行動1 攻撃手》</DisplayName>
            <DisplayFormat>%d</DisplayFormat>
            <Maximum>1</Maximum>
            <Increment>1</Increment>
            <SortID>21000</SortID>
        </Field>
        <Field Def="u8 isSpell">
            <DisplayName>《行動1 スペルフラグ》</DisplayName>
            <Enum>BOOL_CIRCLECROSS_TYPE</Enum>
            <DisplayFormat>%d</DisplayFormat>
            <Maximum>1</Maximum>
            <Increment>1</Increment>
            <SortID>20210</SortID>
        </Field>
        <Field Def="u8 bladeCtrlType">
            <DisplayName>《行動1 近接制御タイプ》</DisplayName>
            <Enum>BLADE_CTRL_TYPE</Enum>
            <Maximum>9999</Maximum>
            <Increment>1</Increment>
            <SortID>20110</SortID>
        </Field>
        <Field Def="s32 bulletId00 = -1">
            <DisplayName>《行動1 BulletID_1》</DisplayName>
            <DisplayFormat>%d</DisplayFormat>
            <EditFlags>Wrap</EditFlags>
            <Minimum>-1</Minimum>
            <Maximum>1e+09</Maximum>
            <Increment>1</Increment>
            <SortID>20100</SortID>
        </Field>
        <Field Def="s32 bulletId01 = -1">
            <DisplayName>《行動1 BulletID_2》</DisplayName>
            <DisplayFormat>%d</DisplayFormat>
            <EditFlags>Wrap</EditFlags>
            <Minimum>-1</Minimum>
            <Maximum>1e+09</Maximum>
            <Increment>1</Increment>
            <SortID>20100</SortID>
        </Field>
        <Field Def="s32 bulletId02 = -1">
            <DisplayName>《行動1 BulletID_3》</DisplayName>
            <DisplayFormat>%d</DisplayFormat>
            <EditFlags>Wrap</EditFlags>
            <Minimum>-1</Minimum>
            <Maximum>1e+09</Maximum>
            <Increment>1</Increment>
            <SortID>20100</SortID>
        </Field>
        <Field Def="f32 shotStanceTime">
            <DisplayName>《行動1 射撃構え時間》</DisplayName>
            <DisplayFormat>%f</DisplayFormat>
            <EditFlags>Wrap</EditFlags>
            <Maximum>60</Maximum>
            <Increment>0.1</Increment>
            <SortID>20100</SortID>
        </Field>
        <Field Def="f32 attackRange = 1">
            <DisplayName>《行動1 歩行攻撃攻撃範囲》</DisplayName>
            <DisplayFormat>%f</DisplayFormat>
            <Maximum>9999</Maximum>
            <Increment>0.1</Increment>
            <SortID>20200</SortID>
        </Field>
        <Field Def="f32 fAttackBackSwingSpeed = 1">
            <DisplayName>《行動1 攻撃開始部速度倍率》</DisplayName>
            <DisplayFormat>%f</DisplayFormat>
            <Minimum>0.1</Minimum>
            <Maximum>9999</Maximum>
            <Increment>0.1</Increment>
            <SortID>20200</SortID>
        </Field>
        <Field Def="f32 fAttackFollowSwingSpeed = 1">
            <DisplayName>《行動1 攻撃終了部速度倍率》</DisplayName>
            <DisplayFormat>%f</DisplayFormat>
            <Minimum>0.1</Minimum>
            <Maximum>9999</Maximum>
            <Increment>0.1</Increment>
            <SortID>20200</SortID>
        </Field>
        <Field Def="f32 fAttackEstimateFutureTime">
            <DisplayName>《行動1 位置予測時間》</DisplayName>
            <DisplayFormat>%f</DisplayFormat>
            <Maximum>9999</Maximum>
            <Increment>0.1</Increment>
            <SortID>20200</SortID>
        </Field>
        <Field Def="angle32 fAttackAngle">
            <DisplayName>《行動1 角度補正[deg]》</DisplayName>
            <DisplayFormat>%f</DisplayFormat>
            <Minimum>-180</Minimum>
            <Maximum>180</Maximum>
            <Increment>0.1</Increment>
            <SortID>20200</SortID>
        </Field>
        <Field Def="f32 fAttackRotateHigh">
            <DisplayName>《行動1 旋回補間開始距離[m]》</DisplayName>
            <DisplayFormat>%f</DisplayFormat>
            <Maximum>100</Maximum>
            <Increment>0.1</Increment>
            <SortID>20200</SortID>
        </Field>
        <Field Def="f32 fAttackRotateLow">
            <DisplayName>《行動1 旋回補間終了距離[m]》</DisplayName>
            <DisplayFormat>%f</DisplayFormat>
            <Maximum>100</Maximum>
            <Increment>0.1</Increment>
            <SortID>20200</SortID>
        </Field>
        <Field Def="u32 chantSfx">
            <DisplayName>《行動1 詠唱SFX》</DisplayName>
            <Enum>ENEMY_SHOT_SFX_PARAM_ENUM</Enum>
            <DisplayFormat>%d</DisplayFormat>
            <Maximum>1</Maximum>
            <Increment>1</Increment>
            <SortID>20200</SortID>
        </Field>
        <Field Def="f32 reloadTimeMin">
            <DisplayName>《行動1 最小リロード時間》</DisplayName>
            <DisplayFormat>%f</DisplayFormat>
            <Maximum>999</Maximum>
            <Increment>0.1</Increment>
            <SortID>20300</SortID>
        </Field>
        <Field Def="f32 reloadTimeMax">
            <DisplayName>《行動1 最大リロード時間》</DisplayName>
            <DisplayFormat>%f</DisplayFormat>
            <Maximum>999</Maximum>
            <Increment>0.1</Increment>
            <SortID>20300</SortID>
        </Field>
        <Field Def="s32 damageId00 = -1">
            <DisplayName>《行動2 ダメージID_1》</DisplayName>
            <DisplayFormat>%d</DisplayFormat>
            <EditFlags>Wrap</EditFlags>
            <Minimum>-1</Minimum>
            <Maximum>1e+09</Maximum>
            <Increment>1</Increment>
            <SortID>30000</SortID>
        </Field>
        <Field Def="s32 damageId01 = -1">
            <DisplayName>《行動2 ダメージID_2》</DisplayName>
            <DisplayFormat>%d</DisplayFormat>
            <EditFlags>Wrap</EditFlags>
            <Minimum>-1</Minimum>
            <Maximum>1e+09</Maximum>
            <Increment>1</Increment>
            <SortID>30000</SortID>
        </Field>
        <Field Def="s32 damageId02 = -1">
            <DisplayName>《行動2 ダメージID_3》</DisplayName>
            <DisplayFormat>%d</DisplayFormat>
            <EditFlags>Wrap</EditFlags>
            <Minimum>-1</Minimum>
            <Maximum>1e+09</Maximum>
            <Increment>1</Increment>
            <SortID>30000</SortID>
        </Field>
        <Field Def="s32 grabDamageId00 = -1">
            <DisplayName>《行動2 投げダメージID_1》</DisplayName>
            <DisplayFormat>%d</DisplayFormat>
            <EditFlags>Wrap</EditFlags>
            <Minimum>-1</Minimum>
            <Maximum>1e+09</Maximum>
            <Increment>1</Increment>
            <SortID>30000</SortID>
        </Field>
        <Field Def="s32 grabDamageId01 = -1">
            <DisplayName>《行動2 投げダメージID_2》</DisplayName>
            <DisplayFormat>%d</DisplayFormat>
            <EditFlags>Wrap</EditFlags>
            <Minimum>-1</Minimum>
            <Maximum>1e+09</Maximum>
            <Increment>1</Increment>
            <SortID>30000</SortID>
        </Field>
        <Field Def="s32 grabDamageId02 = -1">
            <DisplayName>《行動2 投げダメージID_3》</DisplayName>
            <DisplayFormat>%d</DisplayFormat>
            <EditFlags>Wrap</EditFlags>
            <Minimum>-1</Minimum>
            <Maximum>1e+09</Maximum>
            <Increment>1</Increment>
            <SortID>30000</SortID>
        </Field>
        <Field Def="u32 attackWalkMoveAttack">
            <DisplayName>《行動2 歩行攻撃ID》</DisplayName>
            <Enum>ENEMY_ATTACK_TYPE</Enum>
            <DisplayFormat>%d</DisplayFormat>
            <EditFlags>Wrap</EditFlags>
            <Maximum>9999999</Maximum>
            <Increment>1</Increment>
            <SortID>30000</SortID>
        </Field>
        <Field Def="u8 attackInvincible">
            <DisplayName>《行動2 割り込み不可タイプ》</DisplayName>
            <Enum>NON_INTERRUPTIBLE_TYPE</Enum>
            <EditFlags>Wrap</EditFlags>
            <Maximum>1</Maximum>
            <Increment>1</Increment>
            <SortID>30000</SortID>
        </Field>
        <Field Def="u8 handType">
            <DisplayName>《行動2 攻撃手》</DisplayName>
            <DisplayFormat>%d</DisplayFormat>
            <Maximum>1</Maximum>
            <Increment>1</Increment>
            <SortID>31000</SortID>
        </Field>
        <Field Def="u8 isSpell">
            <DisplayName>《行動2 スペルフラグ》</DisplayName>
            <Enum>BOOL_CIRCLECROSS_TYPE</Enum>
            <DisplayFormat>%d</DisplayFormat>
            <Maximum>1</Maximum>
            <Increment>1</Increment>
            <SortID>30210</SortID>
        </Field>
        <Field Def="u8 bladeCtrlType">
            <DisplayName>《行動2 近接制御タイプ》</DisplayName>
            <Enum>BLADE_CTRL_TYPE</Enum>
            <Maximum>9999</Maximum>
            <Increment>1</Increment>
            <SortID>30110</SortID>
        </Field>
        <Field Def="s32 bulletId00 = -1">
            <DisplayName>《行動2 BulletID_1》</DisplayName>
            <DisplayFormat>%d</DisplayFormat>
            <EditFlags>Wrap</EditFlags>
            <Minimum>-1</Minimum>
            <Maximum>1e+09</Maximum>
            <Increment>1</Increment>
            <SortID>30100</SortID>
        </Field>
        <Field Def="s32 bulletId01 = -1">
            <DisplayName>《行動2 BulletID_2》</DisplayName>
            <DisplayFormat>%d</DisplayFormat>
            <EditFlags>Wrap</EditFlags>
            <Minimum>-1</Minimum>
            <Maximum>1e+09</Maximum>
            <Increment>1</Increment>
            <SortID>30100</SortID>
        </Field>
        <Field Def="s32 bulletId02 = -1">
            <DisplayName>《行動2 BulletID_3》</DisplayName>
            <DisplayFormat>%d</DisplayFormat>
            <EditFlags>Wrap</EditFlags>
            <Minimum>-1</Minimum>
            <Maximum>1e+09</Maximum>
            <Increment>1</Increment>
            <SortID>30100</SortID>
        </Field>
        <Field Def="f32 shotStanceTime">
            <DisplayName>《行動2 射撃構え時間》</DisplayName>
            <DisplayFormat>%f</DisplayFormat>
            <EditFlags>Wrap</EditFlags>
            <Maximum>60</Maximum>
            <Increment>0.1</Increment>
            <SortID>30100</SortID>
        </Field>
        <Field Def="f32 attackRange = 1">
            <DisplayName>《行動2 歩行攻撃攻撃範囲》</DisplayName>
            <DisplayFormat>%f</DisplayFormat>
            <Maximum>9999</Maximum>
            <Increment>0.1</Increment>
            <SortID>30200</SortID>
        </Field>
        <Field Def="f32 fAttackBackSwingSpeed = 1">
            <DisplayName>《行動2 攻撃開始部速度倍率》</DisplayName>
            <DisplayFormat>%f</DisplayFormat>
            <Minimum>0.1</Minimum>
            <Maximum>9999</Maximum>
            <Increment>0.1</Increment>
            <SortID>30200</SortID>
        </Field>
        <Field Def="f32 fAttackFollowSwingSpeed = 1">
            <DisplayName>《行動2 攻撃終了部速度倍率》</DisplayName>
            <DisplayFormat>%f</DisplayFormat>
            <Minimum>0.1</Minimum>
            <Maximum>9999</Maximum>
            <Increment>0.1</Increment>
            <SortID>30200</SortID>
        </Field>
        <Field Def="f32 fAttackEstimateFutureTime">
            <DisplayName>《行動2 位置予測時間》</DisplayName>
            <DisplayFormat>%f</DisplayFormat>
            <Maximum>9999</Maximum>
            <Increment>0.1</Increment>
            <SortID>30200</SortID>
        </Field>
        <Field Def="angle32 fAttackAngle">
            <DisplayName>《行動2 角度補正[deg]》</DisplayName>
            <DisplayFormat>%f</DisplayFormat>
            <Minimum>-180</Minimum>
            <Maximum>180</Maximum>
            <Increment>0.1</Increment>
            <SortID>30200</SortID>
        </Field>
        <Field Def="f32 fAttackRotateHigh">
            <DisplayName>《行動2 旋回補間開始距離[m]》</DisplayName>
            <DisplayFormat>%f</DisplayFormat>
            <Maximum>100</Maximum>
            <Increment>0.1</Increment>
            <SortID>30200</SortID>
        </Field>
        <Field Def="f32 fAttackRotateLow">
            <DisplayName>《行動2 旋回補間終了距離[m]》</DisplayName>
            <DisplayFormat>%f</DisplayFormat>
            <Maximum>100</Maximum>
            <Increment>0.1</Increment>
            <SortID>30200</SortID>
        </Field>
        <Field Def="u32 chantSfx">
            <DisplayName>《行動2 詠唱SFX》</DisplayName>
            <Enum>ENEMY_SHOT_SFX_PARAM_ENUM</Enum>
            <DisplayFormat>%d</DisplayFormat>
            <Maximum>1</Maximum>
            <Increment>1</Increment>
            <SortID>30200</SortID>
        </Field>
        <Field Def="f32 reloadTimeMin">
            <DisplayName>《行動2 最小リロード時間》</DisplayName>
            <DisplayFormat>%f</DisplayFormat>
            <Maximum>999</Maximum>
            <Increment>0.1</Increment>
            <SortID>30300</SortID>
        </Field>
        <Field Def="f32 reloadTimeMax">
            <DisplayName>《行動2 最大リロード時間》</DisplayName>
            <DisplayFormat>%f</DisplayFormat>
            <Maximum>999</Maximum>
            <Increment>0.1</Increment>
            <SortID>30300</SortID>
        </Field>
        <Field Def="s32 damageId00 = -1">
            <DisplayName>《行動3 ダメージID_1》</DisplayName>
            <DisplayFormat>%d</DisplayFormat>
            <EditFlags>Wrap</EditFlags>
            <Minimum>-1</Minimum>
            <Maximum>1e+09</Maximum>
            <Increment>1</Increment>
            <SortID>40000</SortID>
        </Field>
        <Field Def="s32 damageId01 = -1">
            <DisplayName>《行動3 ダメージID_2》</DisplayName>
            <DisplayFormat>%d</DisplayFormat>
            <EditFlags>Wrap</EditFlags>
            <Minimum>-1</Minimum>
            <Maximum>1e+09</Maximum>
            <Increment>1</Increment>
            <SortID>40000</SortID>
        </Field>
        <Field Def="s32 damageId02 = -1">
            <DisplayName>《行動3 ダメージID_3》</DisplayName>
            <DisplayFormat>%d</DisplayFormat>
            <EditFlags>Wrap</EditFlags>
            <Minimum>-1</Minimum>
            <Maximum>1e+09</Maximum>
            <Increment>1</Increment>
            <SortID>40000</SortID>
        </Field>
        <Field Def="s32 grabDamageId00 = -1">
            <DisplayName>《行動3 投げダメージID_1》</DisplayName>
            <DisplayFormat>%d</DisplayFormat>
            <EditFlags>Wrap</EditFlags>
            <Minimum>-1</Minimum>
            <Maximum>1e+09</Maximum>
            <Increment>1</Increment>
            <SortID>40000</SortID>
        </Field>
        <Field Def="s32 grabDamageId01 = -1">
            <DisplayName>《行動3 投げダメージID_2》</DisplayName>
            <DisplayFormat>%d</DisplayFormat>
            <EditFlags>Wrap</EditFlags>
            <Minimum>-1</Minimum>
            <Maximum>1e+09</Maximum>
            <Increment>1</Increment>
            <SortID>40000</SortID>
        </Field>
        <Field Def="s32 grabDamageId02 = -1">
            <DisplayName>《行動3 投げダメージID_3》</DisplayName>
            <DisplayFormat>%d</DisplayFormat>
            <EditFlags>Wrap</EditFlags>
            <Minimum>-1</Minimum>
            <Maximum>1e+09</Maximum>
            <Increment>1</Increment>
            <SortID>40000</SortID>
        </Field>
        <Field Def="u32 attackWalkMoveAttack">
            <DisplayName>《行動3 歩行攻撃ID》</DisplayName>
            <Enum>ENEMY_ATTACK_TYPE</Enum>
            <DisplayFormat>%d</DisplayFormat>
            <EditFlags>Wrap</EditFlags>
            <Maximum>9999999</Maximum>
            <Increment>1</Increment>
            <SortID>40000</SortID>
        </Field>
        <Field Def="u8 attackInvincible">
            <DisplayName>《行動3 割り込み不可タイプ》</DisplayName>
            <Enum>NON_INTERRUPTIBLE_TYPE</Enum>
            <EditFlags>Wrap</EditFlags>
            <Maximum>1</Maximum>
            <Increment>1</Increment>
            <SortID>40000</SortID>
        </Field>
        <Field Def="u8 handType">
            <DisplayName>《行動3 攻撃手》</DisplayName>
            <DisplayFormat>%d</DisplayFormat>
            <Maximum>1</Maximum>
            <Increment>1</Increment>
            <SortID>41000</SortID>
        </Field>
        <Field Def="u8 isSpell">
            <DisplayName>《行動3 スペルフラグ》</DisplayName>
            <Enum>BOOL_CIRCLECROSS_TYPE</Enum>
            <DisplayFormat>%d</DisplayFormat>
            <Maximum>1</Maximum>
            <Increment>1</Increment>
            <SortID>40210</SortID>
        </Field>
        <Field Def="u8 bladeCtrlType">
            <DisplayName>《行動3 近接制御タイプ》</DisplayName>
            <Enum>BLADE_CTRL_TYPE</Enum>
            <Maximum>9999</Maximum>
            <Increment>1</Increment>
            <SortID>40110</SortID>
        </Field>
        <Field Def="s32 bulletId00 = -1">
            <DisplayName>《行動3 BulletID_1》</DisplayName>
            <DisplayFormat>%d</DisplayFormat>
            <EditFlags>Wrap</EditFlags>
            <Minimum>-1</Minimum>
            <Maximum>1e+09</Maximum>
            <Increment>1</Increment>
            <SortID>40100</SortID>
        </Field>
        <Field Def="s32 bulletId01 = -1">
            <DisplayName>《行動3 BulletID_2》</DisplayName>
            <DisplayFormat>%d</DisplayFormat>
            <EditFlags>Wrap</EditFlags>
            <Minimum>-1</Minimum>
            <Maximum>1e+09</Maximum>
            <Increment>1</Increment>
            <SortID>40100</SortID>
        </Field>
        <Field Def="s32 bulletId02 = -1">
            <DisplayName>《行動3 BulletID_3》</DisplayName>
            <DisplayFormat>%d</DisplayFormat>
            <EditFlags>Wrap</EditFlags>
            <Minimum>-1</Minimum>
            <Maximum>1e+09</Maximum>
            <Increment>1</Increment>
            <SortID>40100</SortID>
        </Field>
        <Field Def="f32 shotStanceTime">
            <DisplayName>《行動3 射撃構え時間》</DisplayName>
            <DisplayFormat>%f</DisplayFormat>
            <EditFlags>Wrap</EditFlags>
            <Maximum>60</Maximum>
            <Increment>0.1</Increment>
            <SortID>40100</SortID>
        </Field>
        <Field Def="f32 attackRange = 1">
            <DisplayName>《行動3 歩行攻撃攻撃範囲》</DisplayName>
            <DisplayFormat>%f</DisplayFormat>
            <Maximum>9999</Maximum>
            <Increment>0.1</Increment>
            <SortID>40200</SortID>
        </Field>
        <Field Def="f32 fAttackBackSwingSpeed = 1">
            <DisplayName>《行動3 攻撃開始部速度倍率》</DisplayName>
            <DisplayFormat>%f</DisplayFormat>
            <Minimum>0.1</Minimum>
            <Maximum>9999</Maximum>
            <Increment>0.1</Increment>
            <SortID>40200</SortID>
        </Field>
        <Field Def="f32 fAttackFollowSwingSpeed = 1">
            <DisplayName>《行動3 攻撃終了部速度倍率》</DisplayName>
            <DisplayFormat>%f</DisplayFormat>
            <Minimum>0.1</Minimum>
            <Maximum>9999</Maximum>
            <Increment>0.1</Increment>
            <SortID>40200</SortID>
        </Field>
        <Field Def="f32 fAttackEstimateFutureTime">
            <DisplayName>《行動3 位置予測時間》</DisplayName>
            <DisplayFormat>%f</DisplayFormat>
            <Maximum>9999</Maximum>
            <Increment>0.1</Increment>
            <SortID>40200</SortID>
        </Field>
        <Field Def="angle32 fAttackAngle">
            <DisplayName>《行動3 角度補正[deg]》</DisplayName>
            <DisplayFormat>%f</DisplayFormat>
            <Minimum>-180</Minimum>
            <Maximum>180</Maximum>
            <Increment>0.1</Increment>
            <SortID>40200</SortID>
        </Field>
        <Field Def="f32 fAttackRotateHigh">
            <DisplayName>《行動3 旋回補間開始距離[m]》</DisplayName>
            <DisplayFormat>%f</DisplayFormat>
            <Maximum>100</Maximum>
            <Increment>0.1</Increment>
            <SortID>40200</SortID>
        </Field>
        <Field Def="f32 fAttackRotateLow">
            <DisplayName>《行動3 旋回補間終了距離[m]》</DisplayName>
            <DisplayFormat>%f</DisplayFormat>
            <Maximum>100</Maximum>
            <Increment>0.1</Increment>
            <SortID>40200</SortID>
        </Field>
        <Field Def="u32 chantSfx">
            <DisplayName>《行動3 詠唱SFX》</DisplayName>
            <Enum>ENEMY_SHOT_SFX_PARAM_ENUM</Enum>
            <DisplayFormat>%d</DisplayFormat>
            <Maximum>1</Maximum>
            <Increment>1</Increment>
            <SortID>40200</SortID>
        </Field>
        <Field Def="f32 reloadTimeMin">
            <DisplayName>《行動3 最小リロード時間》</DisplayName>
            <DisplayFormat>%f</DisplayFormat>
            <Maximum>999</Maximum>
            <Increment>0.1</Increment>
            <SortID>40300</SortID>
        </Field>
        <Field Def="f32 reloadTimeMax">
            <DisplayName>《行動3 最大リロード時間》</DisplayName>
            <DisplayFormat>%f</DisplayFormat>
            <Maximum>999</Maximum>
            <Increment>0.1</Increment>
            <SortID>40300</SortID>
        </Field>
        <Field Def="s32 damageId00 = -1">
            <DisplayName>《行動4 ダメージID_1》</DisplayName>
            <DisplayFormat>%d</DisplayFormat>
            <EditFlags>Wrap</EditFlags>
            <Minimum>-1</Minimum>
            <Maximum>1e+09</Maximum>
            <Increment>1</Increment>
            <SortID>50000</SortID>
        </Field>
        <Field Def="s32 damageId01 = -1">
            <DisplayName>《行動4 ダメージID_2》</DisplayName>
            <DisplayFormat>%d</DisplayFormat>
            <EditFlags>Wrap</EditFlags>
            <Minimum>-1</Minimum>
            <Maximum>1e+09</Maximum>
            <Increment>1</Increment>
            <SortID>50000</SortID>
        </Field>
        <Field Def="s32 damageId02 = -1">
            <DisplayName>《行動4 ダメージID_3》</DisplayName>
            <DisplayFormat>%d</DisplayFormat>
            <EditFlags>Wrap</EditFlags>
            <Minimum>-1</Minimum>
            <Maximum>1e+09</Maximum>
            <Increment>1</Increment>
            <SortID>50000</SortID>
        </Field>
        <Field Def="s32 grabDamageId00 = -1">
            <DisplayName>《行動4 投げダメージID_1》</DisplayName>
            <DisplayFormat>%d</DisplayFormat>
            <EditFlags>Wrap</EditFlags>
            <Minimum>-1</Minimum>
            <Maximum>1e+09</Maximum>
            <Increment>1</Increment>
            <SortID>50000</SortID>
        </Field>
        <Field Def="s32 grabDamageId01 = -1">
            <DisplayName>《行動4 投げダメージID_2》</DisplayName>
            <DisplayFormat>%d</DisplayFormat>
            <EditFlags>Wrap</EditFlags>
            <Minimum>-1</Minimum>
            <Maximum>1e+09</Maximum>
            <Increment>1</Increment>
            <SortID>50000</SortID>
        </Field>
        <Field Def="s32 grabDamageId02 = -1">
            <DisplayName>《行動4 投げダメージID_3》</DisplayName>
            <DisplayFormat>%d</DisplayFormat>
            <EditFlags>Wrap</EditFlags>
            <Minimum>-1</Minimum>
            <Maximum>1e+09</Maximum>
            <Increment>1</Increment>
            <SortID>50000</SortID>
        </Field>
        <Field Def="u32 attackWalkMoveAttack">
            <DisplayName>《行動4 歩行攻撃ID》</DisplayName>
            <Enum>ENEMY_ATTACK_TYPE</Enum>
            <DisplayFormat>%d</DisplayFormat>
            <EditFlags>Wrap</EditFlags>
            <Maximum>9999999</Maximum>
            <Increment>1</Increment>
            <SortID>50000</SortID>
        </Field>
        <Field Def="u8 attackInvincible">
            <DisplayName>《行動4 割り込み不可タイプ》</DisplayName>
            <Enum>NON_INTERRUPTIBLE_TYPE</Enum>
            <EditFlags>Wrap</EditFlags>
            <Maximum>1</Maximum>
            <Increment>1</Increment>
            <SortID>50000</SortID>
        </Field>
        <Field Def="u8 handType">
            <DisplayName>《行動4 攻撃手》</DisplayName>
            <DisplayFormat>%d</DisplayFormat>
            <Maximum>1</Maximum>
            <Increment>1</Increment>
            <SortID>51000</SortID>
        </Field>
        <Field Def="u8 isSpell">
            <DisplayName>《行動4 スペルフラグ》</DisplayName>
            <Enum>BOOL_CIRCLECROSS_TYPE</Enum>
            <DisplayFormat>%d</DisplayFormat>
            <Maximum>1</Maximum>
            <Increment>1</Increment>
            <SortID>50210</SortID>
        </Field>
        <Field Def="u8 bladeCtrlType">
            <DisplayName>《行動4 近接制御タイプ》</DisplayName>
            <Enum>BLADE_CTRL_TYPE</Enum>
            <Maximum>9999</Maximum>
            <Increment>1</Increment>
            <SortID>50110</SortID>
        </Field>
        <Field Def="s32 bulletId00 = -1">
            <DisplayName>《行動4 BulletID_1》</DisplayName>
            <DisplayFormat>%d</DisplayFormat>
            <EditFlags>Wrap</EditFlags>
            <Minimum>-1</Minimum>
            <Maximum>1e+09</Maximum>
            <Increment>1</Increment>
            <SortID>50100</SortID>
        </Field>
        <Field Def="s32 bulletId01 = -1">
            <DisplayName>《行動4 BulletID_2》</DisplayName>
            <DisplayFormat>%d</DisplayFormat>
            <EditFlags>Wrap</EditFlags>
            <Minimum>-1</Minimum>
            <Maximum>1e+09</Maximum>
            <Increment>1</Increment>
            <SortID>50100</SortID>
        </Field>
        <Field Def="s32 bulletId02 = -1">
            <DisplayName>《行動4 BulletID_3》</DisplayName>
            <DisplayFormat>%d</DisplayFormat>
            <EditFlags>Wrap</EditFlags>
            <Minimum>-1</Minimum>
            <Maximum>1e+09</Maximum>
            <Increment>1</Increment>
            <SortID>50100</SortID>
        </Field>
        <Field Def="f32 shotStanceTime">
            <DisplayName>《行動4 射撃構え時間》</DisplayName>
            <DisplayFormat>%f</DisplayFormat>
            <EditFlags>Wrap</EditFlags>
            <Maximum>60</Maximum>
            <Increment>0.1</Increment>
            <SortID>50100</SortID>
        </Field>
        <Field Def="f32 attackRange = 1">
            <DisplayName>《行動4 歩行攻撃攻撃範囲》</DisplayName>
            <DisplayFormat>%f</DisplayFormat>
            <Maximum>9999</Maximum>
            <Increment>0.1</Increment>
            <SortID>50200</SortID>
        </Field>
        <Field Def="f32 fAttackBackSwingSpeed = 1">
            <DisplayName>《行動4 攻撃開始部速度倍率》</DisplayName>
            <DisplayFormat>%f</DisplayFormat>
            <Minimum>0.1</Minimum>
            <Maximum>9999</Maximum>
            <Increment>0.1</Increment>
            <SortID>50200</SortID>
        </Field>
        <Field Def="f32 fAttackFollowSwingSpeed = 1">
            <DisplayName>《行動4 攻撃終了部速度倍率》</DisplayName>
            <DisplayFormat>%f</DisplayFormat>
            <Minimum>0.1</Minimum>
            <Maximum>9999</Maximum>
            <Increment>0.1</Increment>
            <SortID>50200</SortID>
        </Field>
        <Field Def="f32 fAttackEstimateFutureTime">
            <DisplayName>《行動4 位置予測時間》</DisplayName>
            <DisplayFormat>%f</DisplayFormat>
            <Maximum>9999</Maximum>
            <Increment>0.1</Increment>
            <SortID>50200</SortID>
        </Field>
        <Field Def="angle32 fAttackAngle">
            <DisplayName>《行動4 角度補正[deg]》</DisplayName>
            <DisplayFormat>%f</DisplayFormat>
            <Minimum>-180</Minimum>
            <Maximum>180</Maximum>
            <Increment>0.1</Increment>
            <SortID>50200</SortID>
        </Field>
        <Field Def="f32 fAttackRotateHigh">
            <DisplayName>《行動4 旋回補間開始距離[m]》</DisplayName>
            <DisplayFormat>%f</DisplayFormat>
            <Maximum>100</Maximum>
            <Increment>0.1</Increment>
            <SortID>50200</SortID>
        </Field>
        <Field Def="f32 fAttackRotateLow">
            <DisplayName>《行動4 旋回補間終了距離[m]》</DisplayName>
            <DisplayFormat>%f</DisplayFormat>
            <Maximum>100</Maximum>
            <Increment>0.1</Increment>
            <SortID>50200</SortID>
        </Field>
        <Field Def="u32 chantSfx">
            <DisplayName>《行動4 詠唱SFX》</DisplayName>
            <Enum>ENEMY_SHOT_SFX_PARAM_ENUM</Enum>
            <DisplayFormat>%d</DisplayFormat>
            <Maximum>1</Maximum>
            <Increment>1</Increment>
            <SortID>50200</SortID>
        </Field>
        <Field Def="f32 reloadTimeMin">
            <DisplayName>《行動4 最小リロード時間》</DisplayName>
            <DisplayFormat>%f</DisplayFormat>
            <Maximum>999</Maximum>
            <Increment>0.1</Increment>
            <SortID>50300</SortID>
        </Field>
        <Field Def="f32 reloadTimeMax">
            <DisplayName>《行動4 最大リロード時間》</DisplayName>
            <DisplayFormat>%f</DisplayFormat>
            <Maximum>999</Maximum>
            <Increment>0.1</Increment>
            <SortID>50300</SortID>
        </Field>
        <Field Def="s32 damageId00 = -1">
            <DisplayName>《行動5 ダメージID_1》</DisplayName>
            <DisplayFormat>%d</DisplayFormat>
            <EditFlags>Wrap</EditFlags>
            <Minimum>-1</Minimum>
            <Maximum>1e+09</Maximum>
            <Increment>1</Increment>
            <SortID>60000</SortID>
        </Field>
        <Field Def="s32 damageId01 = -1">
            <DisplayName>《行動5 ダメージID_2》</DisplayName>
            <DisplayFormat>%d</DisplayFormat>
            <EditFlags>Wrap</EditFlags>
            <Minimum>-1</Minimum>
            <Maximum>1e+09</Maximum>
            <Increment>1</Increment>
            <SortID>60000</SortID>
        </Field>
        <Field Def="s32 damageId02 = -1">
            <DisplayName>《行動5 ダメージID_3》</DisplayName>
            <DisplayFormat>%d</DisplayFormat>
            <EditFlags>Wrap</EditFlags>
            <Minimum>-1</Minimum>
            <Maximum>1e+09</Maximum>
            <Increment>1</Increment>
            <SortID>60000</SortID>
        </Field>
        <Field Def="s32 grabDamageId00 = -1">
            <DisplayName>《行動5 投げダメージID_1》</DisplayName>
            <DisplayFormat>%d</DisplayFormat>
            <EditFlags>Wrap</EditFlags>
            <Minimum>-1</Minimum>
            <Maximum>1e+09</Maximum>
            <Increment>1</Increment>
            <SortID>60000</SortID>
        </Field>
        <Field Def="s32 grabDamageId01 = -1">
            <DisplayName>《行動5 投げダメージID_2》</DisplayName>
            <DisplayFormat>%d</DisplayFormat>
            <EditFlags>Wrap</EditFlags>
            <Minimum>-1</Minimum>
            <Maximum>1e+09</Maximum>
            <Increment>1</Increment>
            <SortID>60000</SortID>
        </Field>
        <Field Def="s32 grabDamageId02 = -1">
            <DisplayName>《行動5 投げダメージID_3》</DisplayName>
            <DisplayFormat>%d</DisplayFormat>
            <EditFlags>Wrap</EditFlags>
            <Minimum>-1</Minimum>
            <Maximum>1e+09</Maximum>
            <Increment>1</Increment>
            <SortID>60000</SortID>
        </Field>
        <Field Def="u32 attackWalkMoveAttack">
            <DisplayName>《行動5 歩行攻撃ID》</DisplayName>
            <Enum>ENEMY_ATTACK_TYPE</Enum>
            <DisplayFormat>%d</DisplayFormat>
            <EditFlags>Wrap</EditFlags>
            <Maximum>9999999</Maximum>
            <Increment>1</Increment>
            <SortID>60000</SortID>
        </Field>
        <Field Def="u8 attackInvincible">
            <DisplayName>《行動5 割り込み不可タイプ》</DisplayName>
            <Enum>NON_INTERRUPTIBLE_TYPE</Enum>
            <EditFlags>Wrap</EditFlags>
            <Maximum>1</Maximum>
            <Increment>1</Increment>
            <SortID>60000</SortID>
        </Field>
        <Field Def="u8 handType">
            <DisplayName>《行動5 攻撃手》</DisplayName>
            <DisplayFormat>%d</DisplayFormat>
            <Maximum>1</Maximum>
            <Increment>1</Increment>
            <SortID>61000</SortID>
        </Field>
        <Field Def="u8 isSpell">
            <DisplayName>《行動5 スペルフラグ》</DisplayName>
            <Enum>BOOL_CIRCLECROSS_TYPE</Enum>
            <DisplayFormat>%d</DisplayFormat>
            <Maximum>1</Maximum>
            <Increment>1</Increment>
            <SortID>60210</SortID>
        </Field>
        <Field Def="u8 bladeCtrlType">
            <DisplayName>《行動5 近接制御タイプ》</DisplayName>
            <Enum>BLADE_CTRL_TYPE</Enum>
            <Maximum>9999</Maximum>
            <Increment>1</Increment>
            <SortID>60110</SortID>
        </Field>
        <Field Def="s32 bulletId00 = -1">
            <DisplayName>《行動5 BulletID_1》</DisplayName>
            <DisplayFormat>%d</DisplayFormat>
            <EditFlags>Wrap</EditFlags>
            <Minimum>-1</Minimum>
            <Maximum>1e+09</Maximum>
            <Increment>1</Increment>
            <SortID>60100</SortID>
        </Field>
        <Field Def="s32 bulletId01 = -1">
            <DisplayName>《行動5 BulletID_2》</DisplayName>
            <DisplayFormat>%d</DisplayFormat>
            <EditFlags>Wrap</EditFlags>
            <Minimum>-1</Minimum>
            <Maximum>1e+09</Maximum>
            <Increment>1</Increment>
            <SortID>60100</SortID>
        </Field>
        <Field Def="s32 bulletId02 = -1">
            <DisplayName>《行動5 BulletID_3》</DisplayName>
            <DisplayFormat>%d</DisplayFormat>
            <EditFlags>Wrap</EditFlags>
            <Minimum>-1</Minimum>
            <Maximum>1e+09</Maximum>
            <Increment>1</Increment>
            <SortID>60100</SortID>
        </Field>
        <Field Def="f32 shotStanceTime">
            <DisplayName>《行動5 射撃構え時間》</DisplayName>
            <DisplayFormat>%f</DisplayFormat>
            <EditFlags>Wrap</EditFlags>
            <Maximum>60</Maximum>
            <Increment>0.1</Increment>
            <SortID>60100</SortID>
        </Field>
        <Field Def="f32 attackRange = 1">
            <DisplayName>《行動5 歩行攻撃攻撃範囲》</DisplayName>
            <DisplayFormat>%f</DisplayFormat>
            <Maximum>9999</Maximum>
            <Increment>0.1</Increment>
            <SortID>60200</SortID>
        </Field>
        <Field Def="f32 fAttackBackSwingSpeed = 1">
            <DisplayName>《行動5 攻撃開始部速度倍率》</DisplayName>
            <DisplayFormat>%f</DisplayFormat>
            <Minimum>0.1</Minimum>
            <Maximum>9999</Maximum>
            <Increment>0.1</Increment>
            <SortID>60200</SortID>
        </Field>
        <Field Def="f32 fAttackFollowSwingSpeed = 1">
            <DisplayName>《行動5 攻撃終了部速度倍率》</DisplayName>
            <DisplayFormat>%f</DisplayFormat>
            <Minimum>0.1</Minimum>
            <Maximum>9999</Maximum>
            <Increment>0.1</Increment>
            <SortID>60200</SortID>
        </Field>
        <Field Def="f32 fAttackEstimateFutureTime">
            <DisplayName>《行動5 位置予測時間》</DisplayName>
            <DisplayFormat>%f</DisplayFormat>
            <Maximum>9999</Maximum>
            <Increment>0.1</Increment>
            <SortID>60200</SortID>
        </Field>
        <Field Def="angle32 fAttackAngle">
            <DisplayName>《行動5 角度補正[deg]》</DisplayName>
            <DisplayFormat>%f</DisplayFormat>
            <Minimum>-180</Minimum>
            <Maximum>180</Maximum>
            <Increment>0.1</Increment>
            <SortID>60200</SortID>
        </Field>
        <Field Def="f32 fAttackRotateHigh">
            <DisplayName>《行動5 旋回補間開始距離[m]》</DisplayName>
            <DisplayFormat>%f</DisplayFormat>
            <Maximum>100</Maximum>
            <Increment>0.1</Increment>
            <SortID>60200</SortID>
        </Field>
        <Field Def="f32 fAttackRotateLow">
            <DisplayName>《行動5 旋回補間終了距離[m]》</DisplayName>
            <DisplayFormat>%f</DisplayFormat>
            <Maximum>100</Maximum>
            <Increment>0.1</Increment>
            <SortID>60200</SortID>
        </Field>
        <Field Def="u32 chantSfx">
            <DisplayName>《行動5 詠唱SFX》</DisplayName>
            <Enum>ENEMY_SHOT_SFX_PARAM_ENUM</Enum>
            <DisplayFormat>%d</DisplayFormat>
            <Maximum>1</Maximum>
            <Increment>1</Increment>
            <SortID>60200</SortID>
        </Field>
        <Field Def="f32 reloadTimeMin">
            <DisplayName>《行動5 最小リロード時間》</DisplayName>
            <DisplayFormat>%f</DisplayFormat>
            <Maximum>999</Maximum>
            <Increment>0.1</Increment>
            <SortID>60300</SortID>
        </Field>
        <Field Def="f32 reloadTimeMax">
            <DisplayName>《行動5 最大リロード時間》</DisplayName>
            <DisplayFormat>%f</DisplayFormat>
            <Maximum>999</Maximum>
            <Increment>0.1</Increment>
            <SortID>60300</SortID>
        </Field>
        <Field Def="s32 damageId00 = -1">
            <DisplayName>《行動6 ダメージID_1》</DisplayName>
            <DisplayFormat>%d</DisplayFormat>
            <EditFlags>Wrap</EditFlags>
            <Minimum>-1</Minimum>
            <Maximum>1e+09</Maximum>
            <Increment>1</Increment>
            <SortID>70000</SortID>
        </Field>
        <Field Def="s32 damageId01 = -1">
            <DisplayName>《行動6 ダメージID_2》</DisplayName>
            <DisplayFormat>%d</DisplayFormat>
            <EditFlags>Wrap</EditFlags>
            <Minimum>-1</Minimum>
            <Maximum>1e+09</Maximum>
            <Increment>1</Increment>
            <SortID>70000</SortID>
        </Field>
        <Field Def="s32 damageId02 = -1">
            <DisplayName>《行動6 ダメージID_3》</DisplayName>
            <DisplayFormat>%d</DisplayFormat>
            <EditFlags>Wrap</EditFlags>
            <Minimum>-1</Minimum>
            <Maximum>1e+09</Maximum>
            <Increment>1</Increment>
            <SortID>70000</SortID>
        </Field>
        <Field Def="s32 grabDamageId00 = -1">
            <DisplayName>《行動6 投げダメージID_1》</DisplayName>
            <DisplayFormat>%d</DisplayFormat>
            <EditFlags>Wrap</EditFlags>
            <Minimum>-1</Minimum>
            <Maximum>1e+09</Maximum>
            <Increment>1</Increment>
            <SortID>70000</SortID>
        </Field>
        <Field Def="s32 grabDamageId01 = -1">
            <DisplayName>《行動6 投げダメージID_2》</DisplayName>
            <DisplayFormat>%d</DisplayFormat>
            <EditFlags>Wrap</EditFlags>
            <Minimum>-1</Minimum>
            <Maximum>1e+09</Maximum>
            <Increment>1</Increment>
            <SortID>70000</SortID>
        </Field>
        <Field Def="s32 grabDamageId02 = -1">
            <DisplayName>《行動6 投げダメージID_3》</DisplayName>
            <DisplayFormat>%d</DisplayFormat>
            <EditFlags>Wrap</EditFlags>
            <Minimum>-1</Minimum>
            <Maximum>1e+09</Maximum>
            <Increment>1</Increment>
            <SortID>70000</SortID>
        </Field>
        <Field Def="u32 attackWalkMoveAttack">
            <DisplayName>《行動6 歩行攻撃ID》</DisplayName>
            <Enum>ENEMY_ATTACK_TYPE</Enum>
            <DisplayFormat>%d</DisplayFormat>
            <EditFlags>Wrap</EditFlags>
            <Maximum>9999999</Maximum>
            <Increment>1</Increment>
            <SortID>70000</SortID>
        </Field>
        <Field Def="u8 attackInvincible">
            <DisplayName>《行動6 割り込み不可タイプ》</DisplayName>
            <Enum>NON_INTERRUPTIBLE_TYPE</Enum>
            <EditFlags>Wrap</EditFlags>
            <Maximum>1</Maximum>
            <Increment>1</Increment>
            <SortID>70000</SortID>
        </Field>
        <Field Def="u8 handType">
            <DisplayName>《行動6 攻撃手》</DisplayName>
            <DisplayFormat>%d</DisplayFormat>
            <Maximum>1</Maximum>
            <Increment>1</Increment>
            <SortID>71000</SortID>
        </Field>
        <Field Def="u8 isSpell">
            <DisplayName>《行動6 スペルフラグ》</DisplayName>
            <Enum>BOOL_CIRCLECROSS_TYPE</Enum>
            <DisplayFormat>%d</DisplayFormat>
            <Maximum>1</Maximum>
            <Increment>1</Increment>
            <SortID>70210</SortID>
        </Field>
        <Field Def="u8 bladeCtrlType">
            <DisplayName>《行動6 近接制御タイプ》</DisplayName>
            <Enum>BLADE_CTRL_TYPE</Enum>
            <Maximum>9999</Maximum>
            <Increment>1</Increment>
            <SortID>70110</SortID>
        </Field>
        <Field Def="s32 bulletId00 = -1">
            <DisplayName>《行動6 BulletID_1》</DisplayName>
            <DisplayFormat>%d</DisplayFormat>
            <EditFlags>Wrap</EditFlags>
            <Minimum>-1</Minimum>
            <Maximum>1e+09</Maximum>
            <Increment>1</Increment>
            <SortID>70100</SortID>
        </Field>
        <Field Def="s32 bulletId01 = -1">
            <DisplayName>《行動6 BulletID_2》</DisplayName>
            <DisplayFormat>%d</DisplayFormat>
            <EditFlags>Wrap</EditFlags>
            <Minimum>-1</Minimum>
            <Maximum>1e+09</Maximum>
            <Increment>1</Increment>
            <SortID>70100</SortID>
        </Field>
        <Field Def="s32 bulletId02 = -1">
            <DisplayName>《行動6 BulletID_3》</DisplayName>
            <DisplayFormat>%d</DisplayFormat>
            <EditFlags>Wrap</EditFlags>
            <Minimum>-1</Minimum>
            <Maximum>1e+09</Maximum>
            <Increment>1</Increment>
            <SortID>70100</SortID>
        </Field>
        <Field Def="f32 shotStanceTime">
            <DisplayName>《行動6 射撃構え時間》</DisplayName>
            <DisplayFormat>%f</DisplayFormat>
            <EditFlags>Wrap</EditFlags>
            <Maximum>60</Maximum>
            <Increment>0.1</Increment>
            <SortID>70100</SortID>
        </Field>
        <Field Def="f32 attackRange = 1">
            <DisplayName>《行動6 歩行攻撃攻撃範囲》</DisplayName>
            <DisplayFormat>%f</DisplayFormat>
            <Maximum>9999</Maximum>
            <Increment>0.1</Increment>
            <SortID>70200</SortID>
        </Field>
        <Field Def="f32 fAttackBackSwingSpeed = 1">
            <DisplayName>《行動6 攻撃開始部速度倍率》</DisplayName>
            <DisplayFormat>%f</DisplayFormat>
            <Minimum>0.1</Minimum>
            <Maximum>9999</Maximum>
            <Increment>0.1</Increment>
            <SortID>70200</SortID>
        </Field>
        <Field Def="f32 fAttackFollowSwingSpeed = 1">
            <DisplayName>《行動6 攻撃終了部速度倍率》</DisplayName>
            <DisplayFormat>%f</DisplayFormat>
            <Minimum>0.1</Minimum>
            <Maximum>9999</Maximum>
            <Increment>0.1</Increment>
            <SortID>70200</SortID>
        </Field>
        <Field Def="f32 fAttackEstimateFutureTime">
            <DisplayName>《行動6 位置予測時間》</DisplayName>
            <DisplayFormat>%f</DisplayFormat>
            <Maximum>9999</Maximum>
            <Increment>0.1</Increment>
            <SortID>70200</SortID>
        </Field>
        <Field Def="angle32 fAttackAngle">
            <DisplayName>《行動6 角度補正[deg]》</DisplayName>
            <DisplayFormat>%f</DisplayFormat>
            <Minimum>-180</Minimum>
            <Maximum>180</Maximum>
            <Increment>0.1</Increment>
            <SortID>70200</SortID>
        </Field>
        <Field Def="f32 fAttackRotateHigh">
            <DisplayName>《行動6 旋回補間開始距離[m]》</DisplayName>
            <DisplayFormat>%f</DisplayFormat>
            <Maximum>100</Maximum>
            <Increment>0.1</Increment>
            <SortID>70200</SortID>
        </Field>
        <Field Def="f32 fAttackRotateLow">
            <DisplayName>《行動6 旋回補間終了距離[m]》</DisplayName>
            <DisplayFormat>%f</DisplayFormat>
            <Maximum>100</Maximum>
            <Increment>0.1</Increment>
            <SortID>70200</SortID>
        </Field>
        <Field Def="u32 chantSfx">
            <DisplayName>《行動6 詠唱SFX》</DisplayName>
            <Enum>ENEMY_SHOT_SFX_PARAM_ENUM</Enum>
            <DisplayFormat>%d</DisplayFormat>
            <Maximum>1</Maximum>
            <Increment>1</Increment>
            <SortID>70200</SortID>
        </Field>
        <Field Def="f32 reloadTimeMin">
            <DisplayName>《行動6 最小リロード時間》</DisplayName>
            <DisplayFormat>%f</DisplayFormat>
            <Maximum>999</Maximum>
            <Increment>0.1</Increment>
            <SortID>70300</SortID>
        </Field>
        <Field Def="f32 reloadTimeMax">
            <DisplayName>《行動6 最大リロード時間》</DisplayName>
            <DisplayFormat>%f</DisplayFormat>
            <Maximum>999</Maximum>
            <Increment>0.1</Increment>
            <SortID>70300</SortID>
        </Field>
        <Field Def="s32 damageId00 = -1">
            <DisplayName>《行動7 ダメージID_1》</DisplayName>
            <DisplayFormat>%d</DisplayFormat>
            <EditFlags>Wrap</EditFlags>
            <Minimum>-1</Minimum>
            <Maximum>1e+09</Maximum>
            <Increment>1</Increment>
            <SortID>80000</SortID>
        </Field>
        <Field Def="s32 damageId01 = -1">
            <DisplayName>《行動7 ダメージID_2》</DisplayName>
            <DisplayFormat>%d</DisplayFormat>
            <EditFlags>Wrap</EditFlags>
            <Minimum>-1</Minimum>
            <Maximum>1e+09</Maximum>
            <Increment>1</Increment>
            <SortID>80000</SortID>
        </Field>
        <Field Def="s32 damageId02 = -1">
            <DisplayName>《行動7 ダメージID_3》</DisplayName>
            <DisplayFormat>%d</DisplayFormat>
            <EditFlags>Wrap</EditFlags>
            <Minimum>-1</Minimum>
            <Maximum>1e+09</Maximum>
            <Increment>1</Increment>
            <SortID>80000</SortID>
        </Field>
        <Field Def="s32 grabDamageId00 = -1">
            <DisplayName>《行動7 投げダメージID_1》</DisplayName>
            <DisplayFormat>%d</DisplayFormat>
            <EditFlags>Wrap</EditFlags>
            <Minimum>-1</Minimum>
            <Maximum>1e+09</Maximum>
            <Increment>1</Increment>
            <SortID>80000</SortID>
        </Field>
        <Field Def="s32 grabDamageId01 = -1">
            <DisplayName>《行動7 投げダメージID_2》</DisplayName>
            <DisplayFormat>%d</DisplayFormat>
            <EditFlags>Wrap</EditFlags>
            <Minimum>-1</Minimum>
            <Maximum>1e+09</Maximum>
            <Increment>1</Increment>
            <SortID>80000</SortID>
        </Field>
        <Field Def="s32 grabDamageId02 = -1">
            <DisplayName>《行動7 投げダメージID_3》</DisplayName>
            <DisplayFormat>%d</DisplayFormat>
            <EditFlags>Wrap</EditFlags>
            <Minimum>-1</Minimum>
            <Maximum>1e+09</Maximum>
            <Increment>1</Increment>
            <SortID>80000</SortID>
        </Field>
        <Field Def="u32 attackWalkMoveAttack">
            <DisplayName>《行動7 歩行攻撃ID》</DisplayName>
            <Enum>ENEMY_ATTACK_TYPE</Enum>
            <DisplayFormat>%d</DisplayFormat>
            <EditFlags>Wrap</EditFlags>
            <Maximum>9999999</Maximum>
            <Increment>1</Increment>
            <SortID>80000</SortID>
        </Field>
        <Field Def="u8 attackInvincible">
            <DisplayName>《行動7 割り込み不可タイプ》</DisplayName>
            <Enum>NON_INTERRUPTIBLE_TYPE</Enum>
            <EditFlags>Wrap</EditFlags>
            <Maximum>1</Maximum>
            <Increment>1</Increment>
            <SortID>80000</SortID>
        </Field>
        <Field Def="u8 handType">
            <DisplayName>《行動7 攻撃手》</DisplayName>
            <DisplayFormat>%d</DisplayFormat>
            <Maximum>1</Maximum>
            <Increment>1</Increment>
            <SortID>81000</SortID>
        </Field>
        <Field Def="u8 isSpell">
            <DisplayName>《行動7 スペルフラグ》</DisplayName>
            <Enum>BOOL_CIRCLECROSS_TYPE</Enum>
            <DisplayFormat>%d</DisplayFormat>
            <Maximum>1</Maximum>
            <Increment>1</Increment>
            <SortID>80210</SortID>
        </Field>
        <Field Def="u8 bladeCtrlType">
            <DisplayName>《行動7 近接制御タイプ》</DisplayName>
            <Enum>BLADE_CTRL_TYPE</Enum>
            <Maximum>9999</Maximum>
            <Increment>1</Increment>
            <SortID>80110</SortID>
        </Field>
        <Field Def="s32 bulletId00 = -1">
            <DisplayName>《行動7 BulletID_1》</DisplayName>
            <DisplayFormat>%d</DisplayFormat>
            <EditFlags>Wrap</EditFlags>
            <Minimum>-1</Minimum>
            <Maximum>1e+09</Maximum>
            <Increment>1</Increment>
            <SortID>80100</SortID>
        </Field>
        <Field Def="s32 bulletId01 = -1">
            <DisplayName>《行動7 BulletID_2》</DisplayName>
            <DisplayFormat>%d</DisplayFormat>
            <EditFlags>Wrap</EditFlags>
            <Minimum>-1</Minimum>
            <Maximum>1e+09</Maximum>
            <Increment>1</Increment>
            <SortID>80100</SortID>
        </Field>
        <Field Def="s32 bulletId02 = -1">
            <DisplayName>《行動7 BulletID_3》</DisplayName>
            <DisplayFormat>%d</DisplayFormat>
            <EditFlags>Wrap</EditFlags>
            <Minimum>-1</Minimum>
            <Maximum>1e+09</Maximum>
            <Increment>1</Increment>
            <SortID>80100</SortID>
        </Field>
        <Field Def="f32 shotStanceTime">
            <DisplayName>《行動7 射撃構え時間》</DisplayName>
            <DisplayFormat>%f</DisplayFormat>
            <EditFlags>Wrap</EditFlags>
            <Maximum>60</Maximum>
            <Increment>0.1</Increment>
            <SortID>80100</SortID>
        </Field>
        <Field Def="f32 attackRange = 1">
            <DisplayName>《行動7 歩行攻撃攻撃範囲》</DisplayName>
            <DisplayFormat>%f</DisplayFormat>
            <Maximum>9999</Maximum>
            <Increment>0.1</Increment>
            <SortID>80200</SortID>
        </Field>
        <Field Def="f32 fAttackBackSwingSpeed = 1">
            <DisplayName>《行動7 攻撃開始部速度倍率》</DisplayName>
            <DisplayFormat>%f</DisplayFormat>
            <Minimum>0.1</Minimum>
            <Maximum>9999</Maximum>
            <Increment>0.1</Increment>
            <SortID>80200</SortID>
        </Field>
        <Field Def="f32 fAttackFollowSwingSpeed = 1">
            <DisplayName>《行動7 攻撃終了部速度倍率》</DisplayName>
            <DisplayFormat>%f</DisplayFormat>
            <Minimum>0.1</Minimum>
            <Maximum>9999</Maximum>
            <Increment>0.1</Increment>
            <SortID>80200</SortID>
        </Field>
        <Field Def="f32 fAttackEstimateFutureTime">
            <DisplayName>《行動7 位置予測時間》</DisplayName>
            <DisplayFormat>%f</DisplayFormat>
            <Maximum>9999</Maximum>
            <Increment>0.1</Increment>
            <SortID>80200</SortID>
        </Field>
        <Field Def="angle32 fAttackAngle">
            <DisplayName>《行動7 角度補正[deg]》</DisplayName>
            <DisplayFormat>%f</DisplayFormat>
            <Minimum>-180</Minimum>
            <Maximum>180</Maximum>
            <Increment>0.1</Increment>
            <SortID>80200</SortID>
        </Field>
        <Field Def="f32 fAttackRotateHigh">
            <DisplayName>《行動7 旋回補間開始距離[m]》</DisplayName>
            <DisplayFormat>%f</DisplayFormat>
            <Maximum>100</Maximum>
            <Increment>0.1</Increment>
            <SortID>80200</SortID>
        </Field>
        <Field Def="f32 fAttackRotateLow">
            <DisplayName>《行動7 旋回補間終了距離[m]》</DisplayName>
            <DisplayFormat>%f</DisplayFormat>
            <Maximum>100</Maximum>
            <Increment>0.1</Increment>
            <SortID>80200</SortID>
        </Field>
        <Field Def="u32 chantSfx">
            <DisplayName>《行動7 詠唱SFX》</DisplayName>
            <Enum>ENEMY_SHOT_SFX_PARAM_ENUM</Enum>
            <DisplayFormat>%d</DisplayFormat>
            <Maximum>1</Maximum>
            <Increment>1</Increment>
            <SortID>80200</SortID>
        </Field>
        <Field Def="f32 reloadTimeMin">
            <DisplayName>《行動7 最小リロード時間》</DisplayName>
            <DisplayFormat>%f</DisplayFormat>
            <Maximum>999</Maximum>
            <Increment>0.1</Increment>
            <SortID>80300</SortID>
        </Field>
        <Field Def="f32 reloadTimeMax">
            <DisplayName>《行動7 最大リロード時間》</DisplayName>
            <DisplayFormat>%f</DisplayFormat>
            <Maximum>999</Maximum>
            <Increment>0.1</Increment>
            <SortID>80300</SortID>
        </Field>
        <Field Def="s32 damageId00 = -1">
            <DisplayName>《行動8 ダメージID_1》</DisplayName>
            <DisplayFormat>%d</DisplayFormat>
            <EditFlags>Wrap</EditFlags>
            <Minimum>-1</Minimum>
            <Maximum>1e+09</Maximum>
            <Increment>1</Increment>
            <SortID>90000</SortID>
        </Field>
        <Field Def="s32 damageId01 = -1">
            <DisplayName>《行動8 ダメージID_2》</DisplayName>
            <DisplayFormat>%d</DisplayFormat>
            <EditFlags>Wrap</EditFlags>
            <Minimum>-1</Minimum>
            <Maximum>1e+09</Maximum>
            <Increment>1</Increment>
            <SortID>90000</SortID>
        </Field>
        <Field Def="s32 damageId02 = -1">
            <DisplayName>《行動8 ダメージID_3》</DisplayName>
            <DisplayFormat>%d</DisplayFormat>
            <EditFlags>Wrap</EditFlags>
            <Minimum>-1</Minimum>
            <Maximum>1e+09</Maximum>
            <Increment>1</Increment>
            <SortID>90000</SortID>
        </Field>
        <Field Def="s32 grabDamageId00 = -1">
            <DisplayName>《行動8 投げダメージID_1》</DisplayName>
            <DisplayFormat>%d</DisplayFormat>
            <EditFlags>Wrap</EditFlags>
            <Minimum>-1</Minimum>
            <Maximum>1e+09</Maximum>
            <Increment>1</Increment>
            <SortID>90000</SortID>
        </Field>
        <Field Def="s32 grabDamageId01 = -1">
            <DisplayName>《行動8 投げダメージID_2》</DisplayName>
            <DisplayFormat>%d</DisplayFormat>
            <EditFlags>Wrap</EditFlags>
            <Minimum>-1</Minimum>
            <Maximum>1e+09</Maximum>
            <Increment>1</Increment>
            <SortID>90000</SortID>
        </Field>
        <Field Def="s32 grabDamageId02 = -1">
            <DisplayName>《行動8 投げダメージID_3》</DisplayName>
            <DisplayFormat>%d</DisplayFormat>
            <EditFlags>Wrap</EditFlags>
            <Minimum>-1</Minimum>
            <Maximum>1e+09</Maximum>
            <Increment>1</Increment>
            <SortID>90000</SortID>
        </Field>
        <Field Def="u32 attackWalkMoveAttack">
            <DisplayName>《行動8 歩行攻撃ID》</DisplayName>
            <Enum>ENEMY_ATTACK_TYPE</Enum>
            <DisplayFormat>%d</DisplayFormat>
            <EditFlags>Wrap</EditFlags>
            <Maximum>9999999</Maximum>
            <Increment>1</Increment>
            <SortID>90000</SortID>
        </Field>
        <Field Def="u8 attackInvincible">
            <DisplayName>《行動8 割り込み不可タイプ》</DisplayName>
            <Enum>NON_INTERRUPTIBLE_TYPE</Enum>
            <EditFlags>Wrap</EditFlags>
            <Maximum>1</Maximum>
            <Increment>1</Increment>
            <SortID>90000</SortID>
        </Field>
        <Field Def="u8 handType">
            <DisplayName>《行動8 攻撃手》</DisplayName>
            <DisplayFormat>%d</DisplayFormat>
            <Maximum>1</Maximum>
            <Increment>1</Increment>
            <SortID>91000</SortID>
        </Field>
        <Field Def="u8 isSpell">
            <DisplayName>《行動8 スペルフラグ》</DisplayName>
            <Enum>BOOL_CIRCLECROSS_TYPE</Enum>
            <DisplayFormat>%d</DisplayFormat>
            <Maximum>1</Maximum>
            <Increment>1</Increment>
            <SortID>90210</SortID>
        </Field>
        <Field Def="u8 bladeCtrlType">
            <DisplayName>《行動8 近接制御タイプ》</DisplayName>
            <Enum>BLADE_CTRL_TYPE</Enum>
            <Maximum>9999</Maximum>
            <Increment>1</Increment>
            <SortID>90110</SortID>
        </Field>
        <Field Def="s32 bulletId00 = -1">
            <DisplayName>《行動8 BulletID_1》</DisplayName>
            <DisplayFormat>%d</DisplayFormat>
            <EditFlags>Wrap</EditFlags>
            <Minimum>-1</Minimum>
            <Maximum>1e+09</Maximum>
            <Increment>1</Increment>
            <SortID>90100</SortID>
        </Field>
        <Field Def="s32 bulletId01 = -1">
            <DisplayName>《行動8 BulletID_2》</DisplayName>
            <DisplayFormat>%d</DisplayFormat>
            <EditFlags>Wrap</EditFlags>
            <Minimum>-1</Minimum>
            <Maximum>1e+09</Maximum>
            <Increment>1</Increment>
            <SortID>90100</SortID>
        </Field>
        <Field Def="s32 bulletId02 = -1">
            <DisplayName>《行動8 BulletID_3》</DisplayName>
            <DisplayFormat>%d</DisplayFormat>
            <EditFlags>Wrap</EditFlags>
            <Minimum>-1</Minimum>
            <Maximum>1e+09</Maximum>
            <Increment>1</Increment>
            <SortID>90100</SortID>
        </Field>
        <Field Def="f32 shotStanceTime">
            <DisplayName>《行動8 射撃構え時間》</DisplayName>
            <DisplayFormat>%f</DisplayFormat>
            <EditFlags>Wrap</EditFlags>
            <Maximum>60</Maximum>
            <Increment>0.1</Increment>
            <SortID>90100</SortID>
        </Field>
        <Field Def="f32 attackRange = 1">
            <DisplayName>《行動8 歩行攻撃攻撃範囲》</DisplayName>
            <DisplayFormat>%f</DisplayFormat>
            <Maximum>9999</Maximum>
            <Increment>0.1</Increment>
            <SortID>90200</SortID>
        </Field>
        <Field Def="f32 fAttackBackSwingSpeed = 1">
            <DisplayName>《行動8 攻撃開始部速度倍率》</DisplayName>
            <DisplayFormat>%f</DisplayFormat>
            <Minimum>0.1</Minimum>
            <Maximum>9999</Maximum>
            <Increment>0.1</Increment>
            <SortID>90200</SortID>
        </Field>
        <Field Def="f32 fAttackFollowSwingSpeed = 1">
            <DisplayName>《行動8 攻撃終了部速度倍率》</DisplayName>
            <DisplayFormat>%f</DisplayFormat>
            <Minimum>0.1</Minimum>
            <Maximum>9999</Maximum>
            <Increment>0.1</Increment>
            <SortID>90200</SortID>
        </Field>
        <Field Def="f32 fAttackEstimateFutureTime">
            <DisplayName>《行動8 位置予測時間》</DisplayName>
            <DisplayFormat>%f</DisplayFormat>
            <Maximum>9999</Maximum>
            <Increment>0.1</Increment>
            <SortID>90200</SortID>
        </Field>
        <Field Def="angle32 fAttackAngle">
            <DisplayName>《行動8 角度補正[deg]》</DisplayName>
            <DisplayFormat>%f</DisplayFormat>
            <Minimum>-180</Minimum>
            <Maximum>180</Maximum>
            <Increment>0.1</Increment>
            <SortID>90200</SortID>
        </Field>
        <Field Def="f32 fAttackRotateHigh">
            <DisplayName>《行動8 旋回補間開始距離[m]》</DisplayName>
            <DisplayFormat>%f</DisplayFormat>
            <Maximum>100</Maximum>
            <Increment>0.1</Increment>
            <SortID>90200</SortID>
        </Field>
        <Field Def="f32 fAttackRotateLow">
            <DisplayName>《行動8 旋回補間終了距離[m]》</DisplayName>
            <DisplayFormat>%f</DisplayFormat>
            <Maximum>100</Maximum>
            <Increment>0.1</Increment>
            <SortID>90200</SortID>
        </Field>
        <Field Def="u32 chantSfx">
            <DisplayName>《行動8 詠唱SFX》</DisplayName>
            <Enum>ENEMY_SHOT_SFX_PARAM_ENUM</Enum>
            <DisplayFormat>%d</DisplayFormat>
            <Maximum>1</Maximum>
            <Increment>1</Increment>
            <SortID>90200</SortID>
        </Field>
        <Field Def="f32 reloadTimeMin">
            <DisplayName>《行動8 最小リロード時間》</DisplayName>
            <DisplayFormat>%f</DisplayFormat>
            <Maximum>999</Maximum>
            <Increment>0.1</Increment>
            <SortID>90300</SortID>
        </Field>
        <Field Def="f32 reloadTimeMax">
            <DisplayName>《行動8 最大リロード時間》</DisplayName>
            <DisplayFormat>%f</DisplayFormat>
            <Maximum>999</Maximum>
            <Increment>0.1</Increment>
            <SortID>90300</SortID>
        </Field>
        <Field Def="s32 damageId00 = -1">
            <DisplayName>《行動9 ダメージID_1》</DisplayName>
            <DisplayFormat>%d</DisplayFormat>
            <EditFlags>Wrap</EditFlags>
            <Minimum>-1</Minimum>
            <Maximum>1e+09</Maximum>
            <Increment>1</Increment>
            <SortID>100000</SortID>
        </Field>
        <Field Def="s32 damageId01 = -1">
            <DisplayName>《行動9 ダメージID_2》</DisplayName>
            <DisplayFormat>%d</DisplayFormat>
            <EditFlags>Wrap</EditFlags>
            <Minimum>-1</Minimum>
            <Maximum>1e+09</Maximum>
            <Increment>1</Increment>
            <SortID>100000</SortID>
        </Field>
        <Field Def="s32 damageId02 = -1">
            <DisplayName>《行動9 ダメージID_3》</DisplayName>
            <DisplayFormat>%d</DisplayFormat>
            <EditFlags>Wrap</EditFlags>
            <Minimum>-1</Minimum>
            <Maximum>1e+09</Maximum>
            <Increment>1</Increment>
            <SortID>100000</SortID>
        </Field>
        <Field Def="s32 grabDamageId00 = -1">
            <DisplayName>《行動9 投げダメージID_1》</DisplayName>
            <DisplayFormat>%d</DisplayFormat>
            <EditFlags>Wrap</EditFlags>
            <Minimum>-1</Minimum>
            <Maximum>1e+09</Maximum>
            <Increment>1</Increment>
            <SortID>100000</SortID>
        </Field>
        <Field Def="s32 grabDamageId01 = -1">
            <DisplayName>《行動9 投げダメージID_2》</DisplayName>
            <DisplayFormat>%d</DisplayFormat>
            <EditFlags>Wrap</EditFlags>
            <Minimum>-1</Minimum>
            <Maximum>1e+09</Maximum>
            <Increment>1</Increment>
            <SortID>100000</SortID>
        </Field>
        <Field Def="s32 grabDamageId02 = -1">
            <DisplayName>《行動9 投げダメージID_3》</DisplayName>
            <DisplayFormat>%d</DisplayFormat>
            <EditFlags>Wrap</EditFlags>
            <Minimum>-1</Minimum>
            <Maximum>1e+09</Maximum>
            <Increment>1</Increment>
            <SortID>100000</SortID>
        </Field>
        <Field Def="u32 attackWalkMoveAttack">
            <DisplayName>《行動9 歩行攻撃ID》</DisplayName>
            <Enum>ENEMY_ATTACK_TYPE</Enum>
            <DisplayFormat>%d</DisplayFormat>
            <EditFlags>Wrap</EditFlags>
            <Maximum>9999999</Maximum>
            <Increment>1</Increment>
            <SortID>100000</SortID>
        </Field>
        <Field Def="u8 attackInvincible">
            <DisplayName>《行動9 割り込み不可タイプ》</DisplayName>
            <Enum>NON_INTERRUPTIBLE_TYPE</Enum>
            <EditFlags>Wrap</EditFlags>
            <Maximum>1</Maximum>
            <Increment>1</Increment>
            <SortID>100000</SortID>
        </Field>
        <Field Def="u8 handType">
            <DisplayName>《行動9 攻撃手》</DisplayName>
            <DisplayFormat>%d</DisplayFormat>
            <Maximum>1</Maximum>
            <Increment>1</Increment>
            <SortID>101000</SortID>
        </Field>
        <Field Def="u8 isSpell">
            <DisplayName>《行動9 スペルフラグ》</DisplayName>
            <Enum>BOOL_CIRCLECROSS_TYPE</Enum>
            <DisplayFormat>%d</DisplayFormat>
            <Maximum>1</Maximum>
            <Increment>1</Increment>
            <SortID>100210</SortID>
        </Field>
        <Field Def="u8 bladeCtrlType">
            <DisplayName>《行動9 近接制御タイプ》</DisplayName>
            <Enum>BLADE_CTRL_TYPE</Enum>
            <Maximum>9999</Maximum>
            <Increment>1</Increment>
            <SortID>100110</SortID>
        </Field>
        <Field Def="s32 bulletId00 = -1">
            <DisplayName>《行動9 BulletID_1》</DisplayName>
            <DisplayFormat>%d</DisplayFormat>
            <EditFlags>Wrap</EditFlags>
            <Minimum>-1</Minimum>
            <Maximum>1e+09</Maximum>
            <Increment>1</Increment>
            <SortID>100100</SortID>
        </Field>
        <Field Def="s32 bulletId01 = -1">
            <DisplayName>《行動9 BulletID_2》</DisplayName>
            <DisplayFormat>%d</DisplayFormat>
            <EditFlags>Wrap</EditFlags>
            <Minimum>-1</Minimum>
            <Maximum>1e+09</Maximum>
            <Increment>1</Increment>
            <SortID>100100</SortID>
        </Field>
        <Field Def="s32 bulletId02 = -1">
            <DisplayName>《行動9 BulletID_3》</DisplayName>
            <DisplayFormat>%d</DisplayFormat>
            <EditFlags>Wrap</EditFlags>
            <Minimum>-1</Minimum>
            <Maximum>1e+09</Maximum>
            <Increment>1</Increment>
            <SortID>100100</SortID>
        </Field>
        <Field Def="f32 shotStanceTime">
            <DisplayName>《行動9 射撃構え時間》</DisplayName>
            <DisplayFormat>%f</DisplayFormat>
            <EditFlags>Wrap</EditFlags>
            <Maximum>60</Maximum>
            <Increment>0.1</Increment>
            <SortID>100100</SortID>
        </Field>
        <Field Def="f32 attackRange = 1">
            <DisplayName>《行動9 歩行攻撃攻撃範囲》</DisplayName>
            <DisplayFormat>%f</DisplayFormat>
            <Maximum>9999</Maximum>
            <Increment>0.1</Increment>
            <SortID>100200</SortID>
        </Field>
        <Field Def="f32 fAttackBackSwingSpeed = 1">
            <DisplayName>《行動9 攻撃開始部速度倍率》</DisplayName>
            <DisplayFormat>%f</DisplayFormat>
            <Minimum>0.1</Minimum>
            <Maximum>9999</Maximum>
            <Increment>0.1</Increment>
            <SortID>100200</SortID>
        </Field>
        <Field Def="f32 fAttackFollowSwingSpeed = 1">
            <DisplayName>《行動9 攻撃終了部速度倍率》</DisplayName>
            <DisplayFormat>%f</DisplayFormat>
            <Minimum>0.1</Minimum>
            <Maximum>9999</Maximum>
            <Increment>0.1</Increment>
            <SortID>100200</SortID>
        </Field>
        <Field Def="f32 fAttackEstimateFutureTime">
            <DisplayName>《行動9 位置予測時間》</DisplayName>
            <DisplayFormat>%f</DisplayFormat>
            <Maximum>9999</Maximum>
            <Increment>0.1</Increment>
            <SortID>100200</SortID>
        </Field>
        <Field Def="angle32 fAttackAngle">
            <DisplayName>《行動9 角度補正[deg]》</DisplayName>
            <DisplayFormat>%f</DisplayFormat>
            <Minimum>-180</Minimum>
            <Maximum>180</Maximum>
            <Increment>0.1</Increment>
            <SortID>100200</SortID>
        </Field>
        <Field Def="f32 fAttackRotateHigh">
            <DisplayName>《行動9 旋回補間開始距離[m]》</DisplayName>
            <DisplayFormat>%f</DisplayFormat>
            <Maximum>100</Maximum>
            <Increment>0.1</Increment>
            <SortID>100200</SortID>
        </Field>
        <Field Def="f32 fAttackRotateLow">
            <DisplayName>《行動9 旋回補間終了距離[m]》</DisplayName>
            <DisplayFormat>%f</DisplayFormat>
            <Maximum>100</Maximum>
            <Increment>0.1</Increment>
            <SortID>100200</SortID>
        </Field>
        <Field Def="u32 chantSfx">
            <DisplayName>《行動9 詠唱SFX》</DisplayName>
            <Enum>ENEMY_SHOT_SFX_PARAM_ENUM</Enum>
            <DisplayFormat>%d</DisplayFormat>
            <Maximum>1</Maximum>
            <Increment>1</Increment>
            <SortID>100200</SortID>
        </Field>
        <Field Def="f32 reloadTimeMin">
            <DisplayName>《行動9 最小リロード時間》</DisplayName>
            <DisplayFormat>%f</DisplayFormat>
            <Maximum>999</Maximum>
            <Increment>0.1</Increment>
            <SortID>100300</SortID>
        </Field>
        <Field Def="f32 reloadTimeMax">
            <DisplayName>《行動9 最大リロード時間》</DisplayName>
            <DisplayFormat>%f</DisplayFormat>
            <Maximum>999</Maximum>
            <Increment>0.1</Increment>
            <SortID>100300</SortID>
        </Field>
    </Fields>
</PARAMDEF>
