<?xml version="1.0" encoding="UTF-8"?>
<ParamDef paramType="CRIMINAL_AND_DECEASED_PARAM" bigEndian="false" unicode="true" version="201" unk06="0" byteSize="12">
    <Field name="Unk00" type="u8"/>
    <Field name="Unk01" type="u8"/>
    <Field name="Unk02" type="u8"/>
    <Field name="sinner_sin_points" type="u8">
        <DisplayName>Sin Points - Sinner</DisplayName>
    </Field>
    <Field name="wretch_sin_points" type="u8">
        <DisplayName>Sin Points - Wretch</DisplayName>
    </Field>
    <Field name="hollowing_increase_on_death" type="u8">
        <DisplayName>Hollowing Level Increase on Death</DisplayName>
    </Field>
    <Field name="hollowing_unknown" type="u8">
        <DisplayName>Hollowing Level for Unknown</DisplayName>
    </Field>
    <Field name="hollowing_appearance_change" type="u8">
        <DisplayName>Hollowing Level Appearance Degradation</DisplayName>
    </Field>
    <Field name="hp_min_percent" type="u8">
        <DisplayName>Minimum HP Percentage</DisplayName>
    </Field>
    <Field name="hp_min_percent_wretch" type="u8">
        <DisplayName>Minimum HP Percentage - Wretch</DisplayName>
    </Field>
    <Field name="unknown_percent" type="u8">
        <DisplayName>Unknown Percentage</DisplayName>
    </Field>
    <Field name="unknown_percent_wretch" type="u8">
        <DisplayName>Unknown - Wretch</DisplayName>
    </Field>
</ParamDef>
